__ini__.py
quannengbao/data_oper.py
quannengbao/file_oper.py
quannengbao/fs_price_cal.py
quannengbao/fs_price_lq_cal.py
quannengbao/hdfs.py
quannengbao/image_process.py
quannengbao/lark_admin.py
quannengbao/lark_sheet_oper.py
quannengbao/pickle_process.py
quannengbao/sqlite_oper.py
quannengbao/tqs_oper.py
quannengbao-0.0.14.dist-info/licenses/LICENSE
quannengbao-0.0.14.dist-info/METADATA
quannengbao-0.0.14.dist-info/WHEEL
quannengbao-0.0.14.dist-info/top_level.txt
quannengbao-0.0.14.dist-info/RECORD
